bson-stubs/__init__.pyi
bson-stubs/codec_options.pyi
bson-stubs/dbref.pyi
bson-stubs/errors.pyi
bson-stubs/json_util.pyi
bson-stubs/objectid.pyi
bson-stubs/son.pyi
bson-stubs/timestamp.py
mongoengine-stubs/__init__.pyi
mongoengine-stubs/base.pyi
mongoengine-stubs/connection.pyi
mongoengine-stubs/document.pyi
mongoengine-stubs/errors.pyi
mongoengine-stubs/fields.pyi
mongoengine-stubs/queryset/__init__.pyi
mongoengine-stubs/queryset/queryset.pyi
mongoengine-stubs/queryset/visitor.pyi
mongoengine-stubs/signals.pyi
pymongo-stubs/__init__.pyi
pymongo-stubs/aggregation.pyi
pymongo-stubs/auth.pyi
pymongo-stubs/auth_aws.pyi
pymongo-stubs/bulk.pyi
pymongo-stubs/change_stream.pyi
pymongo-stubs/client_options.pyi
pymongo-stubs/client_session.pyi
pymongo-stubs/collation.pyi
pymongo-stubs/collection.pyi
pymongo-stubs/command_cursor.pyi
pymongo-stubs/common.pyi
pymongo-stubs/compression_support.pyi
pymongo-stubs/cursor.pyi
pymongo-stubs/cursor_manager.pyi
pymongo-stubs/database.pyi
pymongo-stubs/driver_info.pyi
pymongo-stubs/encryption_options.pyi
pymongo-stubs/errors.pyi
pymongo-stubs/helpers.pyi
pymongo-stubs/ismaster.pyi
pymongo-stubs/max_staleness_selectors.pyi
pymongo-stubs/message.pyi
pymongo-stubs/mongo_client.pyi
pymongo-stubs/mongo_replica_set_client.pyi
pymongo-stubs/monitor.pyi
pymongo-stubs/monitoring.pyi
pymongo-stubs/monotonic.pyi
pymongo-stubs/network.pyi
pymongo-stubs/operations.pyi
pymongo-stubs/periodic_executor.pyi
pymongo-stubs/pool.pyi
pymongo-stubs/read_concern.pyi
pymongo-stubs/read_preferences.pyi
pymongo-stubs/response.pyi
pymongo-stubs/results.pyi
pymongo-stubs/saslprep.pyi
pymongo-stubs/server.pyi
pymongo-stubs/server_description.pyi
pymongo-stubs/server_selectors.pyi
pymongo-stubs/server_type.pyi
pymongo-stubs/settings.pyi
pymongo-stubs/socket_checker.pyi
pymongo-stubs/son_manipulator.pyi
pymongo-stubs/srv_resolver.pyi
pymongo-stubs/ssl_context.pyi
pymongo-stubs/ssl_match_hostname.pyi
pymongo-stubs/ssl_support.pyi
pymongo-stubs/thread_util.pyi
mongo_types-0.15.1.dist-info/LICENSE
mongo_types-0.15.1.dist-info/WHEEL
mongo_types-0.15.1.dist-info/METADATA
mongo_types-0.15.1.dist-info/RECORD
