Metadata-Version: 2.1
Name: mongo-types
Version: 0.15.1
Summary: Type stubs for mongoengine w/ basic support for bson and pymongo
Home-page: https://github.com/sbdchd/mongo-types
License: Apache-2.0
Keywords: mongoengine,mongo,types,mypy,stubs
Author: Steve Dignam
Author-email: steve@dignam.xyz
Requires-Python: >=3.7,<4.0
Classifier: License :: OSI Approved :: Apache Software License
Classifier: Programming Language :: Python :: 3
Classifier: Programming Language :: Python :: 3.10
Classifier: Programming Language :: Python :: 3.7
Classifier: Programming Language :: Python :: 3.8
Classifier: Programming Language :: Python :: 3.9
Project-URL: Repository, https://github.com/sbdchd/mongo-types
